PoTrans/__init__.py
PoTrans/cli.py
PoTrans/potrans.py
PoTrans-0.1.7.dist-info/DESCRIPTION.rst
PoTrans-0.1.7.dist-info/METADATA
PoTrans-0.1.7.dist-info/RECORD
PoTrans-0.1.7.dist-info/WHEEL
PoTrans-0.1.7.dist-info/entry_points.txt
PoTrans-0.1.7.dist-info/metadata.json
PoTrans-0.1.7.dist-info/top_level.txt
